pyobs_brot/__init__.py
pyobs_brot/brotdome.py
pyobs_brot/brotroof.py
pyobs_brot/brottelescope.py
pyobs_brot-0.1.6.dist-info/METADATA
pyobs_brot-0.1.6.dist-info/WHEEL
pyobs_brot-0.1.6.dist-info/licenses/LICENSE
pyobs_brot-0.1.6.dist-info/RECORD
