Metadata-Version: 2.4
Name: pyobs-brot
Version: 0.1.6
Summary: pyobs module for BROTlib telescopes
Author-email: Tim-Oliver Husser <thusser@uni-goettingen.de>, Lukas Melzig <lukas.melzig@stud.uni-goettingen.de>
License-Expression: MIT
License-File: LICENSE
Requires-Python: >=3.11
Requires-Dist: astropy<8,>=7.0.1
Requires-Dist: paho-mqtt>=2.1.0
Requires-Dist: pybrotlib>=0.2.0
Requires-Dist: pyobs-core<2,>=1
